[
    {
        "colo": "Default",
        "ip": "2606:4700:90c3:829d:21f0:b0b6:dcf9:1edc",
        "latency": 19,
        "line": "CM",
        "loss": 0,
        "node": "WEBH",
        "speed": 310,
        "time": "2025-01-22 02:24:34"
    },
    {
        "colo": "Default",
        "ip": "2606:4700:90c3:2507:f27d:88f:b4a6:803d",
        "latency": 20,
        "line": "CM",
        "loss": 0,
        "node": "WEBH",
        "speed": 309,
        "time": "2025-01-22 02:24:33"
    },
    {
        "colo": "Default",
        "ip": "2606:4700:90c3:1c17:1235:d9e3:94ee:5d3e",
        "latency": 20,
        "line": "CM",
        "loss": 0,
        "node": "WEBH",
        "speed": 308,
        "time": "2025-01-22 02:24:34"
    },
    {
        "colo": "Default",
        "ip": "2606:4700:8dea:f4d9:1763:2bb8:aa74:4746",
        "latency": 20,
        "line": "CM",
        "loss": 0,
        "node": "WEBH",
        "speed": 308,
        "time": "2025-01-22 02:24:31"
    },
    {
        "colo": "Default",
        "ip": "2606:4700:90c3:d156:5f3d:f3cd:28b1:684a",
        "latency": 20,
        "line": "CM",
        "loss": 0,
        "node": "WEBH",
        "speed": 307,
        "time": "2025-01-22 02:24:32"
    },
    {
        "colo": "Default",
        "ip": "2606:4700:90c3:829d:21f0:b0b6:dcf9:1edc",
        "latency": 19,
        "line": "CT",
        "loss": 0,
        "node": "WEBH",
        "speed": 310,
        "time": "2025-01-22 02:24:34"
    },
    {
        "colo": "Default",
        "ip": "2606:4700:90c3:2507:f27d:88f:b4a6:803d",
        "latency": 20,
        "line": "CT",
        "loss": 0,
        "node": "WEBH",
        "speed": 309,
        "time": "2025-01-22 02:24:33"
    },
    {
        "colo": "Default",
        "ip": "2606:4700:90c3:1c17:1235:d9e3:94ee:5d3e",
        "latency": 20,
        "line": "CT",
        "loss": 0,
        "node": "WEBH",
        "speed": 308,
        "time": "2025-01-22 02:24:34"
    },
    {
        "colo": "Default",
        "ip": "2606:4700:8dea:f4d9:1763:2bb8:aa74:4746",
        "latency": 20,
        "line": "CT",
        "loss": 0,
        "node": "WEBH",
        "speed": 308,
        "time": "2025-01-22 02:24:31"
    },
    {
        "colo": "Default",
        "ip": "2606:4700:90c3:d156:5f3d:f3cd:28b1:684a",
        "latency": 20,
        "line": "CT",
        "loss": 0,
        "node": "WEBH",
        "speed": 307,
        "time": "2025-01-22 02:24:32"
    },
    {
        "colo": "Default",
        "ip": "2606:4700:90c3:829d:21f0:b0b6:dcf9:1edc",
        "latency": 19,
        "line": "CU",
        "loss": 0,
        "node": "WEBH",
        "speed": 310,
        "time": "2025-01-22 02:24:34"
    },
    {
        "colo": "Default",
        "ip": "2606:4700:90c3:2507:f27d:88f:b4a6:803d",
        "latency": 20,
        "line": "CU",
        "loss": 0,
        "node": "WEBH",
        "speed": 309,
        "time": "2025-01-22 02:24:33"
    },
    {
        "colo": "Default",
        "ip": "2606:4700:90c3:1c17:1235:d9e3:94ee:5d3e",
        "latency": 20,
        "line": "CU",
        "loss": 0,
        "node": "WEBH",
        "speed": 308,
        "time": "2025-01-22 02:24:34"
    },
    {
        "colo": "Default",
        "ip": "2606:4700:8dea:f4d9:1763:2bb8:aa74:4746",
        "latency": 20,
        "line": "CU",
        "loss": 0,
        "node": "WEBH",
        "speed": 308,
        "time": "2025-01-22 02:24:31"
    },
    {
        "colo": "Default",
        "ip": "2606:4700:90c3:d156:5f3d:f3cd:28b1:684a",
        "latency": 20,
        "line": "CU",
        "loss": 0,
        "node": "WEBH",
        "speed": 307,
        "time": "2025-01-22 02:24:32"
    }
]