[
    {
        "colo": "Default",
        "ip": "2606:4700:976a:68b5:cbb8:d8e3:9d5a:5551",
        "latency": 3,
        "line": "CM",
        "loss": 0,
        "node": "NETCUP",
        "speed": 547,
        "time": "2025-07-21 01:00:04"
    },
    {
        "colo": "Default",
        "ip": "2606:4700:91b9:772b:8daf:8645:31be:6289",
        "latency": 4,
        "line": "CM",
        "loss": 0,
        "node": "NETCUP",
        "speed": 519,
        "time": "2025-07-21 01:00:04"
    },
    {
        "colo": "Default",
        "ip": "2606:4700:91b9:b4c6:659f:8672:e78e:afbd",
        "latency": 4,
        "line": "CM",
        "loss": 0,
        "node": "NETCUP",
        "speed": 448,
        "time": "2025-07-21 01:00:04"
    },
    {
        "colo": "Default",
        "ip": "2606:4700:1f:198e:b451:d74f:7c15:4d67",
        "latency": 4,
        "line": "CM",
        "loss": 0,
        "node": "NETCUP",
        "speed": 423,
        "time": "2025-07-21 01:00:03"
    },
    {
        "colo": "Default",
        "ip": "2606:4700:3026:b177:7293:1976:22e1:8241",
        "latency": 4,
        "line": "CM",
        "loss": 0,
        "node": "NETCUP",
        "speed": 423,
        "time": "2025-07-21 01:00:04"
    },
    {
        "colo": "Default",
        "ip": "2606:4700:976a:68b5:cbb8:d8e3:9d5a:5551",
        "latency": 3,
        "line": "CT",
        "loss": 0,
        "node": "NETCUP",
        "speed": 547,
        "time": "2025-07-21 01:00:04"
    },
    {
        "colo": "Default",
        "ip": "2606:4700:91b9:772b:8daf:8645:31be:6289",
        "latency": 4,
        "line": "CT",
        "loss": 0,
        "node": "NETCUP",
        "speed": 519,
        "time": "2025-07-21 01:00:04"
    },
    {
        "colo": "Default",
        "ip": "2606:4700:91b9:b4c6:659f:8672:e78e:afbd",
        "latency": 4,
        "line": "CT",
        "loss": 0,
        "node": "NETCUP",
        "speed": 448,
        "time": "2025-07-21 01:00:04"
    },
    {
        "colo": "Default",
        "ip": "2606:4700:1f:198e:b451:d74f:7c15:4d67",
        "latency": 4,
        "line": "CT",
        "loss": 0,
        "node": "NETCUP",
        "speed": 423,
        "time": "2025-07-21 01:00:03"
    },
    {
        "colo": "Default",
        "ip": "2606:4700:3026:b177:7293:1976:22e1:8241",
        "latency": 4,
        "line": "CT",
        "loss": 0,
        "node": "NETCUP",
        "speed": 423,
        "time": "2025-07-21 01:00:04"
    },
    {
        "colo": "Default",
        "ip": "2606:4700:976a:68b5:cbb8:d8e3:9d5a:5551",
        "latency": 3,
        "line": "CU",
        "loss": 0,
        "node": "NETCUP",
        "speed": 547,
        "time": "2025-07-21 01:00:04"
    },
    {
        "colo": "Default",
        "ip": "2606:4700:91b9:772b:8daf:8645:31be:6289",
        "latency": 4,
        "line": "CU",
        "loss": 0,
        "node": "NETCUP",
        "speed": 519,
        "time": "2025-07-21 01:00:04"
    },
    {
        "colo": "Default",
        "ip": "2606:4700:91b9:b4c6:659f:8672:e78e:afbd",
        "latency": 4,
        "line": "CU",
        "loss": 0,
        "node": "NETCUP",
        "speed": 448,
        "time": "2025-07-21 01:00:04"
    },
    {
        "colo": "Default",
        "ip": "2606:4700:1f:198e:b451:d74f:7c15:4d67",
        "latency": 4,
        "line": "CU",
        "loss": 0,
        "node": "NETCUP",
        "speed": 423,
        "time": "2025-07-21 01:00:03"
    },
    {
        "colo": "Default",
        "ip": "2606:4700:3026:b177:7293:1976:22e1:8241",
        "latency": 4,
        "line": "CU",
        "loss": 0,
        "node": "NETCUP",
        "speed": 423,
        "time": "2025-07-21 01:00:04"
    }
]