[
    {
        "colo": "Default",
        "ip": "2606:4700:839d:72b4:44c6:d5e6:2aff:f639",
        "latency": 149,
        "line": "CM",
        "loss": 0,
        "node": "CBUS",
        "speed": 504,
        "time": "2024-12-05 05:19:54"
    },
    {
        "colo": "Default",
        "ip": "2606:4700:91bd:98d7:a7b9:19fa:1a74:d5fa",
        "latency": 149,
        "line": "CM",
        "loss": 0,
        "node": "CBUS",
        "speed": 504,
        "time": "2024-12-05 05:19:54"
    },
    {
        "colo": "Default",
        "ip": "2606:4700:839d:b961:6b2d:3756:53dc:1563",
        "latency": 149,
        "line": "CM",
        "loss": 0,
        "node": "CBUS",
        "speed": 501,
        "time": "2024-12-05 05:19:54"
    },
    {
        "colo": "Default",
        "ip": "2606:4700:839d:b15c:ca0f:f39a:27b1:779c",
        "latency": 146,
        "line": "CM",
        "loss": 0,
        "node": "CBUS",
        "speed": 500,
        "time": "2024-12-05 05:19:54"
    },
    {
        "colo": "Default",
        "ip": "2606:4700:91bd:b508:dc97:bf4e:1137:d165",
        "latency": 149,
        "line": "CM",
        "loss": 0,
        "node": "CBUS",
        "speed": 438,
        "time": "2024-12-05 05:19:54"
    },
    {
        "colo": "Default",
        "ip": "2606:4700:9b00:25f0:8dbd:c186:431:f4f7",
        "latency": 22,
        "line": "CT",
        "loss": 0,
        "node": "WEBH",
        "speed": 309,
        "time": "2024-12-05 05:15:03"
    },
    {
        "colo": "Default",
        "ip": "2606:4700:9b00:c504:bdaa:7e6d:f7e0:95c7",
        "latency": 22,
        "line": "CT",
        "loss": 0,
        "node": "WEBH",
        "speed": 309,
        "time": "2024-12-05 05:15:03"
    },
    {
        "colo": "Default",
        "ip": "2606:4700:9b00:ed71:6494:d034:dac0:cba0",
        "latency": 20,
        "line": "CT",
        "loss": 0,
        "node": "WEBH",
        "speed": 308,
        "time": "2024-12-05 05:15:03"
    },
    {
        "colo": "Default",
        "ip": "2606:4700:9b00:2872:2272:913e:643c:579a",
        "latency": 20,
        "line": "CT",
        "loss": 0,
        "node": "WEBH",
        "speed": 308,
        "time": "2024-12-05 05:15:03"
    },
    {
        "colo": "Default",
        "ip": "2606:4700:9b00:c9be:6f26:8e22:61ae:1af1",
        "latency": 20,
        "line": "CT",
        "loss": 0,
        "node": "WEBH",
        "speed": 307,
        "time": "2024-12-05 05:15:03"
    },
    {
        "colo": "Default",
        "ip": "2606:4700:839d:72b4:44c6:d5e6:2aff:f639",
        "latency": 149,
        "line": "CU",
        "loss": 0,
        "node": "CBUS",
        "speed": 504,
        "time": "2024-12-05 05:19:54"
    },
    {
        "colo": "Default",
        "ip": "2606:4700:91bd:98d7:a7b9:19fa:1a74:d5fa",
        "latency": 149,
        "line": "CU",
        "loss": 0,
        "node": "CBUS",
        "speed": 504,
        "time": "2024-12-05 05:19:54"
    },
    {
        "colo": "Default",
        "ip": "2606:4700:839d:b961:6b2d:3756:53dc:1563",
        "latency": 149,
        "line": "CU",
        "loss": 0,
        "node": "CBUS",
        "speed": 501,
        "time": "2024-12-05 05:19:54"
    },
    {
        "colo": "Default",
        "ip": "2606:4700:839d:b15c:ca0f:f39a:27b1:779c",
        "latency": 146,
        "line": "CU",
        "loss": 0,
        "node": "CBUS",
        "speed": 500,
        "time": "2024-12-05 05:19:54"
    },
    {
        "colo": "Default",
        "ip": "2606:4700:91bd:b508:dc97:bf4e:1137:d165",
        "latency": 149,
        "line": "CU",
        "loss": 0,
        "node": "CBUS",
        "speed": 438,
        "time": "2024-12-05 05:19:54"
    }
]