[
    {
        "colo": "Default",
        "ip": "2606:4700:9a6e:7901:b71f:ee4f:5839:b1d0",
        "latency": 20,
        "line": "CM",
        "loss": 0,
        "node": "WEBH",
        "speed": 309,
        "time": "2025-02-08 14:54:22"
    },
    {
        "colo": "Default",
        "ip": "2606:4700:9a6e:3663:48c7:c0bb:e7f:6d0b",
        "latency": 20,
        "line": "CM",
        "loss": 0,
        "node": "WEBH",
        "speed": 309,
        "time": "2025-02-08 14:54:21"
    },
    {
        "colo": "Default",
        "ip": "2606:4700:9a6e:1445:fac:ab38:6189:dced",
        "latency": 22,
        "line": "CM",
        "loss": 0,
        "node": "WEBH",
        "speed": 308,
        "time": "2025-02-08 14:54:21"
    },
    {
        "colo": "Default",
        "ip": "2606:4700:9a6e:c7bb:ee6e:2a3c:fe0b:fa93",
        "latency": 20,
        "line": "CM",
        "loss": 0,
        "node": "WEBH",
        "speed": 308,
        "time": "2025-02-08 14:54:23"
    },
    {
        "colo": "Default",
        "ip": "2606:4700:9a6e:957a:376c:140b:8594:6e7e",
        "latency": 20,
        "line": "CM",
        "loss": 0,
        "node": "WEBH",
        "speed": 307,
        "time": "2025-02-08 14:54:20"
    },
    {
        "colo": "Default",
        "ip": "2606:4700:9a6e:7901:b71f:ee4f:5839:b1d0",
        "latency": 20,
        "line": "CT",
        "loss": 0,
        "node": "WEBH",
        "speed": 309,
        "time": "2025-02-08 14:54:22"
    },
    {
        "colo": "Default",
        "ip": "2606:4700:9a6e:3663:48c7:c0bb:e7f:6d0b",
        "latency": 20,
        "line": "CT",
        "loss": 0,
        "node": "WEBH",
        "speed": 309,
        "time": "2025-02-08 14:54:21"
    },
    {
        "colo": "Default",
        "ip": "2606:4700:9a6e:1445:fac:ab38:6189:dced",
        "latency": 22,
        "line": "CT",
        "loss": 0,
        "node": "WEBH",
        "speed": 308,
        "time": "2025-02-08 14:54:21"
    },
    {
        "colo": "Default",
        "ip": "2606:4700:9a6e:c7bb:ee6e:2a3c:fe0b:fa93",
        "latency": 20,
        "line": "CT",
        "loss": 0,
        "node": "WEBH",
        "speed": 308,
        "time": "2025-02-08 14:54:23"
    },
    {
        "colo": "Default",
        "ip": "2606:4700:9a6e:957a:376c:140b:8594:6e7e",
        "latency": 20,
        "line": "CT",
        "loss": 0,
        "node": "WEBH",
        "speed": 307,
        "time": "2025-02-08 14:54:20"
    },
    {
        "colo": "Default",
        "ip": "2606:4700:9a6e:7901:b71f:ee4f:5839:b1d0",
        "latency": 20,
        "line": "CU",
        "loss": 0,
        "node": "WEBH",
        "speed": 309,
        "time": "2025-02-08 14:54:22"
    },
    {
        "colo": "Default",
        "ip": "2606:4700:9a6e:3663:48c7:c0bb:e7f:6d0b",
        "latency": 20,
        "line": "CU",
        "loss": 0,
        "node": "WEBH",
        "speed": 309,
        "time": "2025-02-08 14:54:21"
    },
    {
        "colo": "Default",
        "ip": "2606:4700:9a6e:1445:fac:ab38:6189:dced",
        "latency": 22,
        "line": "CU",
        "loss": 0,
        "node": "WEBH",
        "speed": 308,
        "time": "2025-02-08 14:54:21"
    },
    {
        "colo": "Default",
        "ip": "2606:4700:9a6e:c7bb:ee6e:2a3c:fe0b:fa93",
        "latency": 20,
        "line": "CU",
        "loss": 0,
        "node": "WEBH",
        "speed": 308,
        "time": "2025-02-08 14:54:23"
    },
    {
        "colo": "Default",
        "ip": "2606:4700:9a6e:957a:376c:140b:8594:6e7e",
        "latency": 20,
        "line": "CU",
        "loss": 0,
        "node": "WEBH",
        "speed": 307,
        "time": "2025-02-08 14:54:20"
    }
]