[
    {
        "colo": "Default",
        "ip": "2606:4700:3011:bfaf:c9bf:5fed:e724:567a",
        "latency": 11,
        "line": "CM",
        "loss": 0,
        "node": "CBUS",
        "speed": 569,
        "time": "2024-11-09 23:36:01"
    },
    {
        "colo": "Default",
        "ip": "2606:4700:3011:94fc:6ae0:d265:71ab:fc34",
        "latency": 11,
        "line": "CM",
        "loss": 0,
        "node": "CBUS",
        "speed": 566,
        "time": "2024-11-09 23:36:01"
    },
    {
        "colo": "Default",
        "ip": "2606:4700:3011:602f:a606:f88e:5b67:9e7d",
        "latency": 11,
        "line": "CM",
        "loss": 0,
        "node": "CBUS",
        "speed": 546,
        "time": "2024-11-09 23:36:01"
    },
    {
        "colo": "Default",
        "ip": "2606:4700:3011:460a:4044:8f8e:b2a0:d55",
        "latency": 11,
        "line": "CM",
        "loss": 0,
        "node": "CBUS",
        "speed": 522,
        "time": "2024-11-09 23:36:01"
    },
    {
        "colo": "Default",
        "ip": "2606:4700:3011:e52e:4607:722a:2328:23b4",
        "latency": 11,
        "line": "CM",
        "loss": 0,
        "node": "CBUS",
        "speed": 315,
        "time": "2024-11-09 23:36:01"
    },
    {
        "colo": "Default",
        "ip": "2606:4700:9a94:ef3c:cb0a:4f96:c0fa:9b37",
        "latency": 24,
        "line": "CT",
        "loss": 0,
        "node": "WEBH",
        "speed": 308,
        "time": "2024-11-09 23:35:19"
    },
    {
        "colo": "Default",
        "ip": "2606:4700:9a94:e2ac:1486:3b7a:55f9:e2a0",
        "latency": 20,
        "line": "CT",
        "loss": 0,
        "node": "WEBH",
        "speed": 308,
        "time": "2024-11-09 23:35:19"
    },
    {
        "colo": "Default",
        "ip": "2606:4700:9a94:f8ce:45a4:ce33:e07f:86b7",
        "latency": 20,
        "line": "CT",
        "loss": 0,
        "node": "WEBH",
        "speed": 307,
        "time": "2024-11-09 23:35:19"
    },
    {
        "colo": "Default",
        "ip": "2606:4700:9a94:e8c4:3056:7504:2a75:2bc1",
        "latency": 20,
        "line": "CT",
        "loss": 0,
        "node": "WEBH",
        "speed": 307,
        "time": "2024-11-09 23:35:19"
    },
    {
        "colo": "Default",
        "ip": "2606:4700:9a94:6805:8e8c:3b0e:91ae:fcb4",
        "latency": 25,
        "line": "CT",
        "loss": 0,
        "node": "WEBH",
        "speed": 307,
        "time": "2024-11-09 23:35:19"
    },
    {
        "colo": "Default",
        "ip": "2606:4700:3011:bfaf:c9bf:5fed:e724:567a",
        "latency": 11,
        "line": "CU",
        "loss": 0,
        "node": "CBUS",
        "speed": 569,
        "time": "2024-11-09 23:36:01"
    },
    {
        "colo": "Default",
        "ip": "2606:4700:3011:94fc:6ae0:d265:71ab:fc34",
        "latency": 11,
        "line": "CU",
        "loss": 0,
        "node": "CBUS",
        "speed": 566,
        "time": "2024-11-09 23:36:01"
    },
    {
        "colo": "Default",
        "ip": "2606:4700:3011:602f:a606:f88e:5b67:9e7d",
        "latency": 11,
        "line": "CU",
        "loss": 0,
        "node": "CBUS",
        "speed": 546,
        "time": "2024-11-09 23:36:01"
    },
    {
        "colo": "Default",
        "ip": "2606:4700:3011:460a:4044:8f8e:b2a0:d55",
        "latency": 11,
        "line": "CU",
        "loss": 0,
        "node": "CBUS",
        "speed": 522,
        "time": "2024-11-09 23:36:01"
    },
    {
        "colo": "Default",
        "ip": "2606:4700:3011:e52e:4607:722a:2328:23b4",
        "latency": 11,
        "line": "CU",
        "loss": 0,
        "node": "CBUS",
        "speed": 315,
        "time": "2024-11-09 23:36:01"
    }
]