[
    {
        "colo": "Default",
        "ip": "2606:4700:9ad8:2c21:5feb:3426:259a:6f2c",
        "latency": 138,
        "line": "CM",
        "loss": 0,
        "node": "CBUS",
        "speed": 462,
        "time": "2024-05-25 18:10:03"
    },
    {
        "colo": "Default",
        "ip": "2606:4700:9ad8:14d3:7ae1:eeff:ab12:8a51",
        "latency": 137,
        "line": "CM",
        "loss": 0,
        "node": "CBUS",
        "speed": 459,
        "time": "2024-05-25 18:10:02"
    },
    {
        "colo": "Default",
        "ip": "2606:4700:9ad8:a22b:de81:9155:ab21:625e",
        "latency": 137,
        "line": "CM",
        "loss": 0,
        "node": "CBUS",
        "speed": 455,
        "time": "2024-05-25 18:10:02"
    },
    {
        "colo": "Default",
        "ip": "2606:4700:9ad8:d493:615a:45f7:2f73:1f52",
        "latency": 137,
        "line": "CM",
        "loss": 0,
        "node": "CBUS",
        "speed": 455,
        "time": "2024-05-25 18:10:02"
    },
    {
        "colo": "Default",
        "ip": "2606:4700:9ad8:c09a:87a2:b4d2:814:f2e1",
        "latency": 137,
        "line": "CM",
        "loss": 0,
        "node": "CBUS",
        "speed": 435,
        "time": "2024-05-25 18:10:02"
    },
    {
        "colo": "Default",
        "ip": "2606:4700:9ad8:2c21:5feb:3426:259a:6f2c",
        "latency": 138,
        "line": "CT",
        "loss": 0,
        "node": "CBUS",
        "speed": 462,
        "time": "2024-05-25 18:10:03"
    },
    {
        "colo": "Default",
        "ip": "2606:4700:9ad8:14d3:7ae1:eeff:ab12:8a51",
        "latency": 137,
        "line": "CT",
        "loss": 0,
        "node": "CBUS",
        "speed": 459,
        "time": "2024-05-25 18:10:02"
    },
    {
        "colo": "Default",
        "ip": "2606:4700:9ad8:a22b:de81:9155:ab21:625e",
        "latency": 137,
        "line": "CT",
        "loss": 0,
        "node": "CBUS",
        "speed": 455,
        "time": "2024-05-25 18:10:02"
    },
    {
        "colo": "Default",
        "ip": "2606:4700:9ad8:d493:615a:45f7:2f73:1f52",
        "latency": 137,
        "line": "CT",
        "loss": 0,
        "node": "CBUS",
        "speed": 455,
        "time": "2024-05-25 18:10:02"
    },
    {
        "colo": "Default",
        "ip": "2606:4700:9ad8:c09a:87a2:b4d2:814:f2e1",
        "latency": 137,
        "line": "CT",
        "loss": 0,
        "node": "CBUS",
        "speed": 435,
        "time": "2024-05-25 18:10:02"
    },
    {
        "colo": "Default",
        "ip": "2606:4700:9ad8:2c21:5feb:3426:259a:6f2c",
        "latency": 138,
        "line": "CU",
        "loss": 0,
        "node": "CBUS",
        "speed": 462,
        "time": "2024-05-25 18:10:03"
    },
    {
        "colo": "Default",
        "ip": "2606:4700:9ad8:14d3:7ae1:eeff:ab12:8a51",
        "latency": 137,
        "line": "CU",
        "loss": 0,
        "node": "CBUS",
        "speed": 459,
        "time": "2024-05-25 18:10:02"
    },
    {
        "colo": "Default",
        "ip": "2606:4700:9ad8:a22b:de81:9155:ab21:625e",
        "latency": 137,
        "line": "CU",
        "loss": 0,
        "node": "CBUS",
        "speed": 455,
        "time": "2024-05-25 18:10:02"
    },
    {
        "colo": "Default",
        "ip": "2606:4700:9ad8:d493:615a:45f7:2f73:1f52",
        "latency": 137,
        "line": "CU",
        "loss": 0,
        "node": "CBUS",
        "speed": 455,
        "time": "2024-05-25 18:10:02"
    },
    {
        "colo": "Default",
        "ip": "2606:4700:9ad8:c09a:87a2:b4d2:814:f2e1",
        "latency": 137,
        "line": "CU",
        "loss": 0,
        "node": "CBUS",
        "speed": 435,
        "time": "2024-05-25 18:10:02"
    }
]