[
    {
        "colo": "Default",
        "ip": "2606:4700:839b:8b29:c81d:35bb:c0d:5932",
        "latency": 21,
        "line": "CM",
        "loss": 0,
        "node": "WEBH",
        "speed": 310,
        "time": "2025-01-27 06:34:30"
    },
    {
        "colo": "Default",
        "ip": "2606:4700:839b:7cbd:a291:3753:e292:5a54",
        "latency": 21,
        "line": "CM",
        "loss": 0,
        "node": "WEBH",
        "speed": 309,
        "time": "2025-01-27 06:34:31"
    },
    {
        "colo": "Default",
        "ip": "2606:4700:839b:a66e:96f6:b59:7e73:339d",
        "latency": 25,
        "line": "CM",
        "loss": 0,
        "node": "WEBH",
        "speed": 309,
        "time": "2025-01-27 06:34:29"
    },
    {
        "colo": "Default",
        "ip": "2606:4700:839b:1eb:ce9a:c0a8:469:360f",
        "latency": 20,
        "line": "CM",
        "loss": 0,
        "node": "WEBH",
        "speed": 308,
        "time": "2025-01-27 06:34:30"
    },
    {
        "colo": "Default",
        "ip": "2606:4700:3035:2687:9967:6c68:675c:41a",
        "latency": 1,
        "line": "CM",
        "loss": 0,
        "node": "WEBH",
        "speed": 308,
        "time": "2025-01-27 06:34:28"
    },
    {
        "colo": "Default",
        "ip": "2606:4700:839b:8b29:c81d:35bb:c0d:5932",
        "latency": 21,
        "line": "CT",
        "loss": 0,
        "node": "WEBH",
        "speed": 310,
        "time": "2025-01-27 06:34:30"
    },
    {
        "colo": "Default",
        "ip": "2606:4700:839b:7cbd:a291:3753:e292:5a54",
        "latency": 21,
        "line": "CT",
        "loss": 0,
        "node": "WEBH",
        "speed": 309,
        "time": "2025-01-27 06:34:31"
    },
    {
        "colo": "Default",
        "ip": "2606:4700:839b:a66e:96f6:b59:7e73:339d",
        "latency": 25,
        "line": "CT",
        "loss": 0,
        "node": "WEBH",
        "speed": 309,
        "time": "2025-01-27 06:34:29"
    },
    {
        "colo": "Default",
        "ip": "2606:4700:839b:1eb:ce9a:c0a8:469:360f",
        "latency": 20,
        "line": "CT",
        "loss": 0,
        "node": "WEBH",
        "speed": 308,
        "time": "2025-01-27 06:34:30"
    },
    {
        "colo": "Default",
        "ip": "2606:4700:3035:2687:9967:6c68:675c:41a",
        "latency": 1,
        "line": "CT",
        "loss": 0,
        "node": "WEBH",
        "speed": 308,
        "time": "2025-01-27 06:34:28"
    },
    {
        "colo": "Default",
        "ip": "2606:4700:839b:8b29:c81d:35bb:c0d:5932",
        "latency": 21,
        "line": "CU",
        "loss": 0,
        "node": "WEBH",
        "speed": 310,
        "time": "2025-01-27 06:34:30"
    },
    {
        "colo": "Default",
        "ip": "2606:4700:839b:7cbd:a291:3753:e292:5a54",
        "latency": 21,
        "line": "CU",
        "loss": 0,
        "node": "WEBH",
        "speed": 309,
        "time": "2025-01-27 06:34:31"
    },
    {
        "colo": "Default",
        "ip": "2606:4700:839b:a66e:96f6:b59:7e73:339d",
        "latency": 25,
        "line": "CU",
        "loss": 0,
        "node": "WEBH",
        "speed": 309,
        "time": "2025-01-27 06:34:29"
    },
    {
        "colo": "Default",
        "ip": "2606:4700:839b:1eb:ce9a:c0a8:469:360f",
        "latency": 20,
        "line": "CU",
        "loss": 0,
        "node": "WEBH",
        "speed": 308,
        "time": "2025-01-27 06:34:30"
    },
    {
        "colo": "Default",
        "ip": "2606:4700:3035:2687:9967:6c68:675c:41a",
        "latency": 1,
        "line": "CU",
        "loss": 0,
        "node": "WEBH",
        "speed": 308,
        "time": "2025-01-27 06:34:28"
    }
]