[
    {
        "colo": "Default",
        "ip": "2606:4700:9a9a:eb84:94bb:51f8:2e5f:f947",
        "latency": 137,
        "line": "CM",
        "loss": 0,
        "node": "CBUS",
        "speed": 467,
        "time": "2024-04-19 22:44:49"
    },
    {
        "colo": "Default",
        "ip": "2606:4700:9a9a:5db3:a71c:399b:ba59:42f3",
        "latency": 138,
        "line": "CM",
        "loss": 0,
        "node": "CBUS",
        "speed": 465,
        "time": "2024-04-19 22:44:49"
    },
    {
        "colo": "Default",
        "ip": "2606:4700:9a9a:1488:9fb1:a490:4ffc:659e",
        "latency": 138,
        "line": "CM",
        "loss": 0,
        "node": "CBUS",
        "speed": 457,
        "time": "2024-04-19 22:44:49"
    },
    {
        "colo": "Default",
        "ip": "2606:4700:9a9a:bf9b:b55c:f9fe:e815:1253",
        "latency": 138,
        "line": "CM",
        "loss": 0,
        "node": "CBUS",
        "speed": 443,
        "time": "2024-04-19 22:44:49"
    },
    {
        "colo": "Default",
        "ip": "2606:4700:9a9a:c9de:896a:d7c2:88a:9ce2",
        "latency": 138,
        "line": "CM",
        "loss": 0,
        "node": "CBUS",
        "speed": 436,
        "time": "2024-04-19 22:44:49"
    },
    {
        "colo": "Default",
        "ip": "2606:4700:9a9a:eb84:94bb:51f8:2e5f:f947",
        "latency": 137,
        "line": "CT",
        "loss": 0,
        "node": "CBUS",
        "speed": 467,
        "time": "2024-04-19 22:44:49"
    },
    {
        "colo": "Default",
        "ip": "2606:4700:9a9a:5db3:a71c:399b:ba59:42f3",
        "latency": 138,
        "line": "CT",
        "loss": 0,
        "node": "CBUS",
        "speed": 465,
        "time": "2024-04-19 22:44:49"
    },
    {
        "colo": "Default",
        "ip": "2606:4700:9a9a:1488:9fb1:a490:4ffc:659e",
        "latency": 138,
        "line": "CT",
        "loss": 0,
        "node": "CBUS",
        "speed": 457,
        "time": "2024-04-19 22:44:49"
    },
    {
        "colo": "Default",
        "ip": "2606:4700:9a9a:bf9b:b55c:f9fe:e815:1253",
        "latency": 138,
        "line": "CT",
        "loss": 0,
        "node": "CBUS",
        "speed": 443,
        "time": "2024-04-19 22:44:49"
    },
    {
        "colo": "Default",
        "ip": "2606:4700:9a9a:c9de:896a:d7c2:88a:9ce2",
        "latency": 138,
        "line": "CT",
        "loss": 0,
        "node": "CBUS",
        "speed": 436,
        "time": "2024-04-19 22:44:49"
    },
    {
        "colo": "Default",
        "ip": "2606:4700:9a9a:eb84:94bb:51f8:2e5f:f947",
        "latency": 137,
        "line": "CU",
        "loss": 0,
        "node": "CBUS",
        "speed": 467,
        "time": "2024-04-19 22:44:49"
    },
    {
        "colo": "Default",
        "ip": "2606:4700:9a9a:5db3:a71c:399b:ba59:42f3",
        "latency": 138,
        "line": "CU",
        "loss": 0,
        "node": "CBUS",
        "speed": 465,
        "time": "2024-04-19 22:44:49"
    },
    {
        "colo": "Default",
        "ip": "2606:4700:9a9a:1488:9fb1:a490:4ffc:659e",
        "latency": 138,
        "line": "CU",
        "loss": 0,
        "node": "CBUS",
        "speed": 457,
        "time": "2024-04-19 22:44:49"
    },
    {
        "colo": "Default",
        "ip": "2606:4700:9a9a:bf9b:b55c:f9fe:e815:1253",
        "latency": 138,
        "line": "CU",
        "loss": 0,
        "node": "CBUS",
        "speed": 443,
        "time": "2024-04-19 22:44:49"
    },
    {
        "colo": "Default",
        "ip": "2606:4700:9a9a:c9de:896a:d7c2:88a:9ce2",
        "latency": 138,
        "line": "CU",
        "loss": 0,
        "node": "CBUS",
        "speed": 436,
        "time": "2024-04-19 22:44:49"
    }
]