[
    {
        "colo": "Default",
        "ip": "2606:4700:9a9b:37fd:dc2a:4364:5046:4097",
        "latency": 4,
        "line": "CM",
        "loss": 0,
        "node": "NETCUP",
        "speed": 559,
        "time": "2025-07-20 00:50:00"
    },
    {
        "colo": "Default",
        "ip": "2606:4700:90d6:b8a1:a7a7:b1bb:e71d:d65b",
        "latency": 4,
        "line": "CM",
        "loss": 0,
        "node": "NETCUP",
        "speed": 542,
        "time": "2025-07-20 00:49:59"
    },
    {
        "colo": "Default",
        "ip": "2606:4700:28:796b:f6c0:da4b:ce3a:5530",
        "latency": 3,
        "line": "CM",
        "loss": 0,
        "node": "NETCUP",
        "speed": 455,
        "time": "2025-07-20 00:50:00"
    },
    {
        "colo": "Default",
        "ip": "2606:4700:90d7:5dc4:520a:4bdc:cfc4:62d9",
        "latency": 5,
        "line": "CM",
        "loss": 0,
        "node": "NETCUP",
        "speed": 426,
        "time": "2025-07-20 00:50:00"
    },
    {
        "colo": "Default",
        "ip": "2606:4700:28:69a4:c629:3189:e2ff:a9cf",
        "latency": 4,
        "line": "CM",
        "loss": 0,
        "node": "NETCUP",
        "speed": 415,
        "time": "2025-07-20 00:50:00"
    },
    {
        "colo": "Default",
        "ip": "2606:4700:9a9b:37fd:dc2a:4364:5046:4097",
        "latency": 4,
        "line": "CT",
        "loss": 0,
        "node": "NETCUP",
        "speed": 559,
        "time": "2025-07-20 00:50:00"
    },
    {
        "colo": "Default",
        "ip": "2606:4700:90d6:b8a1:a7a7:b1bb:e71d:d65b",
        "latency": 4,
        "line": "CT",
        "loss": 0,
        "node": "NETCUP",
        "speed": 542,
        "time": "2025-07-20 00:49:59"
    },
    {
        "colo": "Default",
        "ip": "2606:4700:28:796b:f6c0:da4b:ce3a:5530",
        "latency": 3,
        "line": "CT",
        "loss": 0,
        "node": "NETCUP",
        "speed": 455,
        "time": "2025-07-20 00:50:00"
    },
    {
        "colo": "Default",
        "ip": "2606:4700:90d7:5dc4:520a:4bdc:cfc4:62d9",
        "latency": 5,
        "line": "CT",
        "loss": 0,
        "node": "NETCUP",
        "speed": 426,
        "time": "2025-07-20 00:50:00"
    },
    {
        "colo": "Default",
        "ip": "2606:4700:28:69a4:c629:3189:e2ff:a9cf",
        "latency": 4,
        "line": "CT",
        "loss": 0,
        "node": "NETCUP",
        "speed": 415,
        "time": "2025-07-20 00:50:00"
    },
    {
        "colo": "Default",
        "ip": "2606:4700:9a9b:37fd:dc2a:4364:5046:4097",
        "latency": 4,
        "line": "CU",
        "loss": 0,
        "node": "NETCUP",
        "speed": 559,
        "time": "2025-07-20 00:50:00"
    },
    {
        "colo": "Default",
        "ip": "2606:4700:90d6:b8a1:a7a7:b1bb:e71d:d65b",
        "latency": 4,
        "line": "CU",
        "loss": 0,
        "node": "NETCUP",
        "speed": 542,
        "time": "2025-07-20 00:49:59"
    },
    {
        "colo": "Default",
        "ip": "2606:4700:28:796b:f6c0:da4b:ce3a:5530",
        "latency": 3,
        "line": "CU",
        "loss": 0,
        "node": "NETCUP",
        "speed": 455,
        "time": "2025-07-20 00:50:00"
    },
    {
        "colo": "Default",
        "ip": "2606:4700:90d7:5dc4:520a:4bdc:cfc4:62d9",
        "latency": 5,
        "line": "CU",
        "loss": 0,
        "node": "NETCUP",
        "speed": 426,
        "time": "2025-07-20 00:50:00"
    },
    {
        "colo": "Default",
        "ip": "2606:4700:28:69a4:c629:3189:e2ff:a9cf",
        "latency": 4,
        "line": "CU",
        "loss": 0,
        "node": "NETCUP",
        "speed": 415,
        "time": "2025-07-20 00:50:00"
    }
]