[
    {
        "colo": "Default",
        "ip": "2606:4700:9768:c0df:f32:6ab:ae70:47bb",
        "latency": 20,
        "line": "CM",
        "loss": 0,
        "node": "WEBH",
        "speed": 308,
        "time": "2025-01-30 07:14:26"
    },
    {
        "colo": "Default",
        "ip": "2606:4700:9768:410d:51a0:e4a6:19f7:97be",
        "latency": 20,
        "line": "CM",
        "loss": 0,
        "node": "WEBH",
        "speed": 308,
        "time": "2025-01-30 07:14:27"
    },
    {
        "colo": "Default",
        "ip": "2606:4700:9768:129c:ad9d:f36c:891:a450",
        "latency": 20,
        "line": "CM",
        "loss": 0,
        "node": "WEBH",
        "speed": 307,
        "time": "2025-01-30 07:14:27"
    },
    {
        "colo": "Default",
        "ip": "2606:4700:9768:ae12:2355:a130:2962:5282",
        "latency": 20,
        "line": "CM",
        "loss": 0,
        "node": "WEBH",
        "speed": 307,
        "time": "2025-01-30 07:14:29"
    },
    {
        "colo": "Default",
        "ip": "2606:4700:9768:eda3:1c2f:da74:90c1:3a01",
        "latency": 25,
        "line": "CM",
        "loss": 0,
        "node": "WEBH",
        "speed": 307,
        "time": "2025-01-30 07:14:28"
    },
    {
        "colo": "Default",
        "ip": "2606:4700:9768:c0df:f32:6ab:ae70:47bb",
        "latency": 20,
        "line": "CT",
        "loss": 0,
        "node": "WEBH",
        "speed": 308,
        "time": "2025-01-30 07:14:26"
    },
    {
        "colo": "Default",
        "ip": "2606:4700:9768:410d:51a0:e4a6:19f7:97be",
        "latency": 20,
        "line": "CT",
        "loss": 0,
        "node": "WEBH",
        "speed": 308,
        "time": "2025-01-30 07:14:27"
    },
    {
        "colo": "Default",
        "ip": "2606:4700:9768:129c:ad9d:f36c:891:a450",
        "latency": 20,
        "line": "CT",
        "loss": 0,
        "node": "WEBH",
        "speed": 307,
        "time": "2025-01-30 07:14:27"
    },
    {
        "colo": "Default",
        "ip": "2606:4700:9768:ae12:2355:a130:2962:5282",
        "latency": 20,
        "line": "CT",
        "loss": 0,
        "node": "WEBH",
        "speed": 307,
        "time": "2025-01-30 07:14:29"
    },
    {
        "colo": "Default",
        "ip": "2606:4700:9768:eda3:1c2f:da74:90c1:3a01",
        "latency": 25,
        "line": "CT",
        "loss": 0,
        "node": "WEBH",
        "speed": 307,
        "time": "2025-01-30 07:14:28"
    },
    {
        "colo": "Default",
        "ip": "2606:4700:9768:c0df:f32:6ab:ae70:47bb",
        "latency": 20,
        "line": "CU",
        "loss": 0,
        "node": "WEBH",
        "speed": 308,
        "time": "2025-01-30 07:14:26"
    },
    {
        "colo": "Default",
        "ip": "2606:4700:9768:410d:51a0:e4a6:19f7:97be",
        "latency": 20,
        "line": "CU",
        "loss": 0,
        "node": "WEBH",
        "speed": 308,
        "time": "2025-01-30 07:14:27"
    },
    {
        "colo": "Default",
        "ip": "2606:4700:9768:129c:ad9d:f36c:891:a450",
        "latency": 20,
        "line": "CU",
        "loss": 0,
        "node": "WEBH",
        "speed": 307,
        "time": "2025-01-30 07:14:27"
    },
    {
        "colo": "Default",
        "ip": "2606:4700:9768:ae12:2355:a130:2962:5282",
        "latency": 20,
        "line": "CU",
        "loss": 0,
        "node": "WEBH",
        "speed": 307,
        "time": "2025-01-30 07:14:29"
    },
    {
        "colo": "Default",
        "ip": "2606:4700:9768:eda3:1c2f:da74:90c1:3a01",
        "latency": 25,
        "line": "CU",
        "loss": 0,
        "node": "WEBH",
        "speed": 307,
        "time": "2025-01-30 07:14:28"
    }
]