[
    {
        "colo": "Default",
        "ip": "2606:4700:8d70:e03e:d671:50e:9f9b:d72e",
        "latency": 137,
        "line": "CM",
        "loss": 0,
        "node": "CBUS",
        "speed": 461,
        "time": "2024-02-15 17:04:57"
    },
    {
        "colo": "Default",
        "ip": "2606:4700:8d70:e131:56bb:65b1:7063:636",
        "latency": 137,
        "line": "CM",
        "loss": 0,
        "node": "CBUS",
        "speed": 457,
        "time": "2024-02-15 17:04:57"
    },
    {
        "colo": "Default",
        "ip": "2606:4700:8d70:2c26:840:e460:7c0b:6ec",
        "latency": 137,
        "line": "CM",
        "loss": 0,
        "node": "CBUS",
        "speed": 453,
        "time": "2024-02-15 17:04:57"
    },
    {
        "colo": "Default",
        "ip": "2606:4700:8d70:fff9:4bdf:4f7c:2010:5f6e",
        "latency": 138,
        "line": "CM",
        "loss": 0,
        "node": "CBUS",
        "speed": 450,
        "time": "2024-02-15 17:04:57"
    },
    {
        "colo": "Default",
        "ip": "2606:4700:8d70:f48b:d4e8:d02c:11b:266b",
        "latency": 138,
        "line": "CM",
        "loss": 0,
        "node": "CBUS",
        "speed": 449,
        "time": "2024-02-15 17:04:57"
    },
    {
        "colo": "Default",
        "ip": "2606:4700:8d70:e03e:d671:50e:9f9b:d72e",
        "latency": 137,
        "line": "CT",
        "loss": 0,
        "node": "CBUS",
        "speed": 461,
        "time": "2024-02-15 17:04:57"
    },
    {
        "colo": "Default",
        "ip": "2606:4700:8d70:e131:56bb:65b1:7063:636",
        "latency": 137,
        "line": "CT",
        "loss": 0,
        "node": "CBUS",
        "speed": 457,
        "time": "2024-02-15 17:04:57"
    },
    {
        "colo": "Default",
        "ip": "2606:4700:8d70:2c26:840:e460:7c0b:6ec",
        "latency": 137,
        "line": "CT",
        "loss": 0,
        "node": "CBUS",
        "speed": 453,
        "time": "2024-02-15 17:04:57"
    },
    {
        "colo": "Default",
        "ip": "2606:4700:8d70:fff9:4bdf:4f7c:2010:5f6e",
        "latency": 138,
        "line": "CT",
        "loss": 0,
        "node": "CBUS",
        "speed": 450,
        "time": "2024-02-15 17:04:57"
    },
    {
        "colo": "Default",
        "ip": "2606:4700:8d70:f48b:d4e8:d02c:11b:266b",
        "latency": 138,
        "line": "CT",
        "loss": 0,
        "node": "CBUS",
        "speed": 449,
        "time": "2024-02-15 17:04:57"
    },
    {
        "colo": "Default",
        "ip": "2606:4700:8d70:e03e:d671:50e:9f9b:d72e",
        "latency": 137,
        "line": "CU",
        "loss": 0,
        "node": "CBUS",
        "speed": 461,
        "time": "2024-02-15 17:04:57"
    },
    {
        "colo": "Default",
        "ip": "2606:4700:8d70:e131:56bb:65b1:7063:636",
        "latency": 137,
        "line": "CU",
        "loss": 0,
        "node": "CBUS",
        "speed": 457,
        "time": "2024-02-15 17:04:57"
    },
    {
        "colo": "Default",
        "ip": "2606:4700:8d70:2c26:840:e460:7c0b:6ec",
        "latency": 137,
        "line": "CU",
        "loss": 0,
        "node": "CBUS",
        "speed": 453,
        "time": "2024-02-15 17:04:57"
    },
    {
        "colo": "Default",
        "ip": "2606:4700:8d70:fff9:4bdf:4f7c:2010:5f6e",
        "latency": 138,
        "line": "CU",
        "loss": 0,
        "node": "CBUS",
        "speed": 450,
        "time": "2024-02-15 17:04:57"
    },
    {
        "colo": "Default",
        "ip": "2606:4700:8d70:f48b:d4e8:d02c:11b:266b",
        "latency": 138,
        "line": "CU",
        "loss": 0,
        "node": "CBUS",
        "speed": 449,
        "time": "2024-02-15 17:04:57"
    }
]