[
    {
        "colo": "Default",
        "ip": "2606:4700:83b4:931f:baf2:c39a:9d45:dd9d",
        "latency": 148,
        "line": "CM",
        "loss": 0,
        "node": "NETCUP",
        "speed": 621,
        "time": "2025-11-01 23:49:52"
    },
    {
        "colo": "Default",
        "ip": "2606:4700:8d73:d0d9:6a09:9331:b1:8c15",
        "latency": 3,
        "line": "CM",
        "loss": 0,
        "node": "NETCUP",
        "speed": 507,
        "time": "2025-11-01 23:49:51"
    },
    {
        "colo": "Default",
        "ip": "2606:4700:9640:db01:ca3a:4c77:f91b:177a",
        "latency": 3,
        "line": "CM",
        "loss": 0,
        "node": "NETCUP",
        "speed": 437,
        "time": "2025-11-01 23:49:51"
    },
    {
        "colo": "Default",
        "ip": "2606:4700:9ad8:e996:eda8:c255:8e0b:b651",
        "latency": 3,
        "line": "CM",
        "loss": 0,
        "node": "NETCUP",
        "speed": 427,
        "time": "2025-11-01 23:49:51"
    },
    {
        "colo": "Default",
        "ip": "2606:4700:9a94:ab40:594a:efb6:a262:84ec",
        "latency": 3,
        "line": "CM",
        "loss": 0,
        "node": "NETCUP",
        "speed": 405,
        "time": "2025-11-01 23:49:51"
    },
    {
        "colo": "Default",
        "ip": "2606:4700:83b4:931f:baf2:c39a:9d45:dd9d",
        "latency": 148,
        "line": "CT",
        "loss": 0,
        "node": "NETCUP",
        "speed": 621,
        "time": "2025-11-01 23:49:52"
    },
    {
        "colo": "Default",
        "ip": "2606:4700:8d73:d0d9:6a09:9331:b1:8c15",
        "latency": 3,
        "line": "CT",
        "loss": 0,
        "node": "NETCUP",
        "speed": 507,
        "time": "2025-11-01 23:49:51"
    },
    {
        "colo": "Default",
        "ip": "2606:4700:9640:db01:ca3a:4c77:f91b:177a",
        "latency": 3,
        "line": "CT",
        "loss": 0,
        "node": "NETCUP",
        "speed": 437,
        "time": "2025-11-01 23:49:51"
    },
    {
        "colo": "Default",
        "ip": "2606:4700:9ad8:e996:eda8:c255:8e0b:b651",
        "latency": 3,
        "line": "CT",
        "loss": 0,
        "node": "NETCUP",
        "speed": 427,
        "time": "2025-11-01 23:49:51"
    },
    {
        "colo": "Default",
        "ip": "2606:4700:9a94:ab40:594a:efb6:a262:84ec",
        "latency": 3,
        "line": "CT",
        "loss": 0,
        "node": "NETCUP",
        "speed": 405,
        "time": "2025-11-01 23:49:51"
    },
    {
        "colo": "Default",
        "ip": "2606:4700:83b4:931f:baf2:c39a:9d45:dd9d",
        "latency": 148,
        "line": "CU",
        "loss": 0,
        "node": "NETCUP",
        "speed": 621,
        "time": "2025-11-01 23:49:52"
    },
    {
        "colo": "Default",
        "ip": "2606:4700:8d73:d0d9:6a09:9331:b1:8c15",
        "latency": 3,
        "line": "CU",
        "loss": 0,
        "node": "NETCUP",
        "speed": 507,
        "time": "2025-11-01 23:49:51"
    },
    {
        "colo": "Default",
        "ip": "2606:4700:9640:db01:ca3a:4c77:f91b:177a",
        "latency": 3,
        "line": "CU",
        "loss": 0,
        "node": "NETCUP",
        "speed": 437,
        "time": "2025-11-01 23:49:51"
    },
    {
        "colo": "Default",
        "ip": "2606:4700:9ad8:e996:eda8:c255:8e0b:b651",
        "latency": 3,
        "line": "CU",
        "loss": 0,
        "node": "NETCUP",
        "speed": 427,
        "time": "2025-11-01 23:49:51"
    },
    {
        "colo": "Default",
        "ip": "2606:4700:9a94:ab40:594a:efb6:a262:84ec",
        "latency": 3,
        "line": "CU",
        "loss": 0,
        "node": "NETCUP",
        "speed": 405,
        "time": "2025-11-01 23:49:51"
    }
]