[
    {
        "colo": "Default",
        "ip": "2606:4700:3025:737c:44a4:f360:c1c6:9c08",
        "latency": 11,
        "line": "CM",
        "loss": 0,
        "node": "CBUS",
        "speed": 618,
        "time": "2024-06-13 23:43:13"
    },
    {
        "colo": "Default",
        "ip": "2606:4700:3025:ef47:b07c:543a:6079:fa34",
        "latency": 12,
        "line": "CM",
        "loss": 0,
        "node": "CBUS",
        "speed": 606,
        "time": "2024-06-13 23:43:13"
    },
    {
        "colo": "Default",
        "ip": "2606:4700:3025:9c36:837c:276f:8228:c9a6",
        "latency": 11,
        "line": "CM",
        "loss": 0,
        "node": "CBUS",
        "speed": 604,
        "time": "2024-06-13 23:43:13"
    },
    {
        "colo": "Default",
        "ip": "2606:4700:3025:d0ed:fe18:9693:baa7:ccaa",
        "latency": 11,
        "line": "CM",
        "loss": 0,
        "node": "CBUS",
        "speed": 597,
        "time": "2024-06-13 23:43:13"
    },
    {
        "colo": "Default",
        "ip": "2606:4700:3025:3867:634d:35b3:db3:86b2",
        "latency": 11,
        "line": "CM",
        "loss": 0,
        "node": "CBUS",
        "speed": 581,
        "time": "2024-06-13 23:43:13"
    },
    {
        "colo": "Default",
        "ip": "2606:4700:3025:737c:44a4:f360:c1c6:9c08",
        "latency": 11,
        "line": "CT",
        "loss": 0,
        "node": "CBUS",
        "speed": 618,
        "time": "2024-06-13 23:43:13"
    },
    {
        "colo": "Default",
        "ip": "2606:4700:3025:ef47:b07c:543a:6079:fa34",
        "latency": 12,
        "line": "CT",
        "loss": 0,
        "node": "CBUS",
        "speed": 606,
        "time": "2024-06-13 23:43:13"
    },
    {
        "colo": "Default",
        "ip": "2606:4700:3025:9c36:837c:276f:8228:c9a6",
        "latency": 11,
        "line": "CT",
        "loss": 0,
        "node": "CBUS",
        "speed": 604,
        "time": "2024-06-13 23:43:13"
    },
    {
        "colo": "Default",
        "ip": "2606:4700:3025:d0ed:fe18:9693:baa7:ccaa",
        "latency": 11,
        "line": "CT",
        "loss": 0,
        "node": "CBUS",
        "speed": 597,
        "time": "2024-06-13 23:43:13"
    },
    {
        "colo": "Default",
        "ip": "2606:4700:3025:3867:634d:35b3:db3:86b2",
        "latency": 11,
        "line": "CT",
        "loss": 0,
        "node": "CBUS",
        "speed": 581,
        "time": "2024-06-13 23:43:13"
    },
    {
        "colo": "Default",
        "ip": "2606:4700:3025:737c:44a4:f360:c1c6:9c08",
        "latency": 11,
        "line": "CU",
        "loss": 0,
        "node": "CBUS",
        "speed": 618,
        "time": "2024-06-13 23:43:13"
    },
    {
        "colo": "Default",
        "ip": "2606:4700:3025:ef47:b07c:543a:6079:fa34",
        "latency": 12,
        "line": "CU",
        "loss": 0,
        "node": "CBUS",
        "speed": 606,
        "time": "2024-06-13 23:43:13"
    },
    {
        "colo": "Default",
        "ip": "2606:4700:3025:9c36:837c:276f:8228:c9a6",
        "latency": 11,
        "line": "CU",
        "loss": 0,
        "node": "CBUS",
        "speed": 604,
        "time": "2024-06-13 23:43:13"
    },
    {
        "colo": "Default",
        "ip": "2606:4700:3025:d0ed:fe18:9693:baa7:ccaa",
        "latency": 11,
        "line": "CU",
        "loss": 0,
        "node": "CBUS",
        "speed": 597,
        "time": "2024-06-13 23:43:13"
    },
    {
        "colo": "Default",
        "ip": "2606:4700:3025:3867:634d:35b3:db3:86b2",
        "latency": 11,
        "line": "CU",
        "loss": 0,
        "node": "CBUS",
        "speed": 581,
        "time": "2024-06-13 23:43:13"
    }
]