[
    {
        "colo": "Default",
        "ip": "2606:4700:9a63:ab6b:d25:c0a9:4c0b:3683",
        "latency": 1,
        "line": "CM",
        "loss": 0,
        "node": "WW_HK",
        "speed": 308,
        "time": "2024-10-11 06:15:41"
    },
    {
        "colo": "Default",
        "ip": "2606:4700:9a63:d2a:3a88:5a1:ec7f:e81d",
        "latency": 1,
        "line": "CM",
        "loss": 0,
        "node": "WW_HK",
        "speed": 308,
        "time": "2024-10-11 06:15:41"
    },
    {
        "colo": "Default",
        "ip": "2606:4700:9a63:4f27:e26b:487c:fb34:7288",
        "latency": 1,
        "line": "CM",
        "loss": 0,
        "node": "WW_HK",
        "speed": 307,
        "time": "2024-10-11 06:15:41"
    },
    {
        "colo": "Default",
        "ip": "2606:4700:9a63:35ec:4f7:bcc9:fda7:1b5a",
        "latency": 1,
        "line": "CM",
        "loss": 0,
        "node": "WW_HK",
        "speed": 307,
        "time": "2024-10-11 06:15:41"
    },
    {
        "colo": "Default",
        "ip": "2606:4700:9a63:1ea2:c99b:bb8a:7f74:9f16",
        "latency": 0,
        "line": "CM",
        "loss": 0,
        "node": "WW_HK",
        "speed": 307,
        "time": "2024-10-11 06:15:41"
    },
    {
        "colo": "Default",
        "ip": "2606:4700:85d7:8170:3f02:69c3:594a:828e",
        "latency": 20,
        "line": "CT",
        "loss": 0,
        "node": "WEBH",
        "speed": 309,
        "time": "2024-10-11 06:15:43"
    },
    {
        "colo": "Default",
        "ip": "2606:4700:85d3:12b3:cf36:2672:9b48:cebc",
        "latency": 19,
        "line": "CT",
        "loss": 0,
        "node": "WEBH",
        "speed": 308,
        "time": "2024-10-11 06:15:41"
    },
    {
        "colo": "Default",
        "ip": "2606:4700:85d7:b1a6:6259:9673:5b87:c",
        "latency": 24,
        "line": "CT",
        "loss": 0,
        "node": "WEBH",
        "speed": 308,
        "time": "2024-10-11 06:15:40"
    },
    {
        "colo": "Default",
        "ip": "2606:4700:85d7:d57d:2c4a:b4d9:20ca:baba",
        "latency": 20,
        "line": "CT",
        "loss": 0,
        "node": "WEBH",
        "speed": 307,
        "time": "2024-10-11 06:15:42"
    },
    {
        "colo": "Default",
        "ip": "2606:4700:85d3:301b:c65a:ad00:7c6d:aefd",
        "latency": 20,
        "line": "CT",
        "loss": 0,
        "node": "WEBH",
        "speed": 307,
        "time": "2024-10-11 06:15:41"
    },
    {
        "colo": "Default",
        "ip": "2606:4700:9a63:ab6b:d25:c0a9:4c0b:3683",
        "latency": 1,
        "line": "CU",
        "loss": 0,
        "node": "WW_HK",
        "speed": 308,
        "time": "2024-10-11 06:15:41"
    },
    {
        "colo": "Default",
        "ip": "2606:4700:9a63:d2a:3a88:5a1:ec7f:e81d",
        "latency": 1,
        "line": "CU",
        "loss": 0,
        "node": "WW_HK",
        "speed": 308,
        "time": "2024-10-11 06:15:41"
    },
    {
        "colo": "Default",
        "ip": "2606:4700:9a63:4f27:e26b:487c:fb34:7288",
        "latency": 1,
        "line": "CU",
        "loss": 0,
        "node": "WW_HK",
        "speed": 307,
        "time": "2024-10-11 06:15:41"
    },
    {
        "colo": "Default",
        "ip": "2606:4700:9a63:35ec:4f7:bcc9:fda7:1b5a",
        "latency": 1,
        "line": "CU",
        "loss": 0,
        "node": "WW_HK",
        "speed": 307,
        "time": "2024-10-11 06:15:41"
    },
    {
        "colo": "Default",
        "ip": "2606:4700:9a63:1ea2:c99b:bb8a:7f74:9f16",
        "latency": 0,
        "line": "CU",
        "loss": 0,
        "node": "WW_HK",
        "speed": 307,
        "time": "2024-10-11 06:15:41"
    }
]