[
    {
        "colo": "Default",
        "ip": "2606:4700:90c2:17ca:249d:3b30:a698:a432",
        "latency": 20,
        "line": "CM",
        "loss": 0,
        "node": "WEBH",
        "speed": 309,
        "time": "2025-02-17 23:44:14"
    },
    {
        "colo": "Default",
        "ip": "2606:4700:5c:f402:8a9:6464:e670:20f5",
        "latency": 1,
        "line": "CM",
        "loss": 0,
        "node": "WEBH",
        "speed": 309,
        "time": "2025-02-17 23:44:13"
    },
    {
        "colo": "Default",
        "ip": "2606:4700:90c2:5bd7:63c3:6bfd:b9b0:56ef",
        "latency": 20,
        "line": "CM",
        "loss": 0,
        "node": "WEBH",
        "speed": 309,
        "time": "2025-02-17 23:44:16"
    },
    {
        "colo": "Default",
        "ip": "2606:4700:5c:3c2d:7237:b4ab:ffbc:4306",
        "latency": 1,
        "line": "CM",
        "loss": 0,
        "node": "WEBH",
        "speed": 308,
        "time": "2025-02-17 23:44:14"
    },
    {
        "colo": "Default",
        "ip": "2606:4700:5c:3f11:423a:18c4:6408:8b7a",
        "latency": 1,
        "line": "CM",
        "loss": 0,
        "node": "WEBH",
        "speed": 307,
        "time": "2025-02-17 23:44:15"
    },
    {
        "colo": "Default",
        "ip": "2606:4700:90c2:17ca:249d:3b30:a698:a432",
        "latency": 20,
        "line": "CT",
        "loss": 0,
        "node": "WEBH",
        "speed": 309,
        "time": "2025-02-17 23:44:14"
    },
    {
        "colo": "Default",
        "ip": "2606:4700:5c:f402:8a9:6464:e670:20f5",
        "latency": 1,
        "line": "CT",
        "loss": 0,
        "node": "WEBH",
        "speed": 309,
        "time": "2025-02-17 23:44:13"
    },
    {
        "colo": "Default",
        "ip": "2606:4700:90c2:5bd7:63c3:6bfd:b9b0:56ef",
        "latency": 20,
        "line": "CT",
        "loss": 0,
        "node": "WEBH",
        "speed": 309,
        "time": "2025-02-17 23:44:16"
    },
    {
        "colo": "Default",
        "ip": "2606:4700:5c:3c2d:7237:b4ab:ffbc:4306",
        "latency": 1,
        "line": "CT",
        "loss": 0,
        "node": "WEBH",
        "speed": 308,
        "time": "2025-02-17 23:44:14"
    },
    {
        "colo": "Default",
        "ip": "2606:4700:5c:3f11:423a:18c4:6408:8b7a",
        "latency": 1,
        "line": "CT",
        "loss": 0,
        "node": "WEBH",
        "speed": 307,
        "time": "2025-02-17 23:44:15"
    },
    {
        "colo": "Default",
        "ip": "2606:4700:90c2:17ca:249d:3b30:a698:a432",
        "latency": 20,
        "line": "CU",
        "loss": 0,
        "node": "WEBH",
        "speed": 309,
        "time": "2025-02-17 23:44:14"
    },
    {
        "colo": "Default",
        "ip": "2606:4700:5c:f402:8a9:6464:e670:20f5",
        "latency": 1,
        "line": "CU",
        "loss": 0,
        "node": "WEBH",
        "speed": 309,
        "time": "2025-02-17 23:44:13"
    },
    {
        "colo": "Default",
        "ip": "2606:4700:90c2:5bd7:63c3:6bfd:b9b0:56ef",
        "latency": 20,
        "line": "CU",
        "loss": 0,
        "node": "WEBH",
        "speed": 309,
        "time": "2025-02-17 23:44:16"
    },
    {
        "colo": "Default",
        "ip": "2606:4700:5c:3c2d:7237:b4ab:ffbc:4306",
        "latency": 1,
        "line": "CU",
        "loss": 0,
        "node": "WEBH",
        "speed": 308,
        "time": "2025-02-17 23:44:14"
    },
    {
        "colo": "Default",
        "ip": "2606:4700:5c:3f11:423a:18c4:6408:8b7a",
        "latency": 1,
        "line": "CU",
        "loss": 0,
        "node": "WEBH",
        "speed": 307,
        "time": "2025-02-17 23:44:15"
    }
]