[
    {
        "colo": "Default",
        "ip": "2606:4700:91bf:42fd:899f:b6c3:679b:d03c",
        "latency": 303,
        "line": "CM",
        "loss": 0,
        "node": "WW_HK",
        "speed": 310,
        "time": "2024-09-15 02:24:56"
    },
    {
        "colo": "Default",
        "ip": "2606:4700:8d74:5ad3:33b7:47d3:b40b:3ec",
        "latency": 34,
        "line": "CM",
        "loss": 0,
        "node": "WW_HK",
        "speed": 310,
        "time": "2024-09-15 02:24:54"
    },
    {
        "colo": "Default",
        "ip": "2606:4700:8d74:48f3:6acf:fc53:2d11:28b9",
        "latency": 35,
        "line": "CM",
        "loss": 0,
        "node": "WW_HK",
        "speed": 309,
        "time": "2024-09-15 02:24:54"
    },
    {
        "colo": "Default",
        "ip": "2606:4700:8d74:a59b:75e2:f9d7:196d:7ff3",
        "latency": 40,
        "line": "CM",
        "loss": 0,
        "node": "WW_HK",
        "speed": 308,
        "time": "2024-09-15 02:24:54"
    },
    {
        "colo": "Default",
        "ip": "2606:4700:91bf:e509:57c:3191:f8b:4b16",
        "latency": 297,
        "line": "CM",
        "loss": 0,
        "node": "WW_HK",
        "speed": 307,
        "time": "2024-09-15 02:24:55"
    },
    {
        "colo": "Default",
        "ip": "2606:4700:9640:2d2c:d368:5262:2310:7f0",
        "latency": 25,
        "line": "CT",
        "loss": 0,
        "node": "WEBH",
        "speed": 310,
        "time": "2024-09-15 02:25:57"
    },
    {
        "colo": "Default",
        "ip": "2606:4700:9640:ee9f:41be:928c:4ac9:c671",
        "latency": 20,
        "line": "CT",
        "loss": 0,
        "node": "WEBH",
        "speed": 310,
        "time": "2024-09-15 02:25:56"
    },
    {
        "colo": "Default",
        "ip": "2606:4700:9640:af11:b89c:d0fa:67f3:36f8",
        "latency": 23,
        "line": "CT",
        "loss": 0,
        "node": "WEBH",
        "speed": 308,
        "time": "2024-09-15 02:25:56"
    },
    {
        "colo": "Default",
        "ip": "2606:4700:9640:7798:35b7:58f1:c10b:a6e9",
        "latency": 19,
        "line": "CT",
        "loss": 0,
        "node": "WEBH",
        "speed": 308,
        "time": "2024-09-15 02:25:56"
    },
    {
        "colo": "Default",
        "ip": "2606:4700:9640:9f0e:fbe9:4193:12c0:c89d",
        "latency": 24,
        "line": "CT",
        "loss": 0,
        "node": "WEBH",
        "speed": 308,
        "time": "2024-09-15 02:25:56"
    },
    {
        "colo": "Default",
        "ip": "2606:4700:91bf:42fd:899f:b6c3:679b:d03c",
        "latency": 303,
        "line": "CU",
        "loss": 0,
        "node": "WW_HK",
        "speed": 310,
        "time": "2024-09-15 02:24:56"
    },
    {
        "colo": "Default",
        "ip": "2606:4700:8d74:5ad3:33b7:47d3:b40b:3ec",
        "latency": 34,
        "line": "CU",
        "loss": 0,
        "node": "WW_HK",
        "speed": 310,
        "time": "2024-09-15 02:24:54"
    },
    {
        "colo": "Default",
        "ip": "2606:4700:8d74:48f3:6acf:fc53:2d11:28b9",
        "latency": 35,
        "line": "CU",
        "loss": 0,
        "node": "WW_HK",
        "speed": 309,
        "time": "2024-09-15 02:24:54"
    },
    {
        "colo": "Default",
        "ip": "2606:4700:8d74:a59b:75e2:f9d7:196d:7ff3",
        "latency": 40,
        "line": "CU",
        "loss": 0,
        "node": "WW_HK",
        "speed": 308,
        "time": "2024-09-15 02:24:54"
    },
    {
        "colo": "Default",
        "ip": "2606:4700:91bf:e509:57c:3191:f8b:4b16",
        "latency": 297,
        "line": "CU",
        "loss": 0,
        "node": "WW_HK",
        "speed": 307,
        "time": "2024-09-15 02:24:55"
    }
]